pyttslib/__init__.py
pyttslib/exceptions.py
pyttslib/tts.py
pyttslib/utils.py
pyttslib-0.1.0.dist-info/licenses/LICENSE
pyttslib-0.1.0.dist-info/METADATA
pyttslib-0.1.0.dist-info/WHEEL
pyttslib-0.1.0.dist-info/top_level.txt
pyttslib-0.1.0.dist-info/RECORD
