Metadata-Version: 2.4
Name: pyttslib
Version: 0.1.0
Summary: A powerful and easy-to-use Python Text-to-Speech library with multiple engine support
Home-page: https://github.com/udaygiri/PyTTSLib
Author: Uday Giri
Author-email: www.udaygiriaparnathi2004@gmail.com
Project-URL: Bug Tracker, https://github.com/udaygiri/PyTTSLib/issues
Project-URL: Documentation, https://github.com/udaygiri/PyTTSLib#readme
Project-URL: Source Code, https://github.com/udaygiri/PyTTSLib
Keywords: text-to-speech,tts,speech synthesis,audio,google-tts,pyttsx3
Classifier: Development Status :: 4 - Beta
Classifier: Intended Audience :: Developers
Classifier: Topic :: Multimedia :: Sound/Audio :: Speech
Classifier: Programming Language :: Python :: 3
Classifier: Programming Language :: Python :: 3.6
Classifier: Programming Language :: Python :: 3.7
Classifier: Programming Language :: Python :: 3.8
Classifier: Programming Language :: Python :: 3.9
Classifier: Programming Language :: Python :: 3.10
Classifier: Programming Language :: Python :: 3.11
Classifier: License :: OSI Approved :: MIT License
Classifier: Operating System :: OS Independent
Requires-Python: >=3.6
License-File: LICENSE
Requires-Dist: pyttsx3>=2.90
Requires-Dist: gtts>=2.2.4
Requires-Dist: playsound>=1.3.0
Dynamic: author
Dynamic: author-email
Dynamic: classifier
Dynamic: description
Dynamic: description-content-type
Dynamic: home-page
Dynamic: keywords
Dynamic: license-file
Dynamic: project-url
Dynamic: requires-dist
Dynamic: requires-python
Dynamic: summary
